aaronsteers/__init__.py
aaronsteers/hello.py
aaronsteers-0.0.1a0.dist-info/WHEEL
aaronsteers-0.0.1a0.dist-info/METADATA
aaronsteers-0.0.1a0.dist-info/RECORD
