Metadata-Version: 2.1
Name: aaronsteers
Version: 0.0.1a0
Summary: It's me, AJ! Hi.
License: Apache 2.0
Author: AJ Steers
Author-email: aaronsteers@gmail.com
Requires-Python: >=3.8,<4.0
Classifier: License :: Other/Proprietary License
Classifier: Programming Language :: Python :: 3
Classifier: Programming Language :: Python :: 3.8
Classifier: Programming Language :: Python :: 3.9
